{"Id":1,"Model":"Model1","SerialNumber":"SN1","Type":0}
{"Id":2,"Model":"Model2","SerialNumber":"SN2","Type":1}
{"Id":3,"Model":"Model3","SerialNumber":"SN3","Type":2}
{"Id":4,"Model":"Model4","SerialNumber":"SN4","Type":0}
{"Id":5,"Model":"Model5","SerialNumber":"SN5","Type":1}
{"Id":6,"Model":"Model6","SerialNumber":"SN6","Type":2}
{"Id":7,"Model":"Model7","SerialNumber":"SN7","Type":0}
{"Id":8,"Model":"Model8","SerialNumber":"SN8","Type":1}
{"Id":9,"Model":"Model9","SerialNumber":"SN9","Type":2}
{"Id":10,"Model":"Model10","SerialNumber":"SN10","Type":0}
{"Id":11,"Model":"Model11","SerialNumber":"SN11","Type":1}
{"Id":12,"Model":"Model12","SerialNumber":"SN12","Type":2}
{"Id":13,"Model":"Model13","SerialNumber":"SN13","Type":0}
{"Id":14,"Model":"Model14","SerialNumber":"SN14","Type":1}
{"Id":15,"Model":"Model15","SerialNumber":"SN15","Type":2}
{"Id":16,"Model":"Model16","SerialNumber":"SN16","Type":0}
{"Id":17,"Model":"Model17","SerialNumber":"SN17","Type":1}
{"Id":18,"Model":"Model18","SerialNumber":"SN18","Type":2}
{"Id":19,"Model":"Model19","SerialNumber":"SN19","Type":0}
{"Id":20,"Model":"Model20","SerialNumber":"SN20","Type":1}
